{
  "dbnya": [
    {
      "username": "Rilyzy",
      "password": "Rilyzy",
      "nomor": "6282282345392"
    },
    {
      "username": "leo",
      "password": "leo",
      "nomor": "6281271247153"
    },
    {
      "username": "corza",
      "password": "za",
      "nomor": "6283891912603"
    },
    {
      "username": "az",
      "password": "azz",
      "nomor": "6285251941527"
    },
    {
      "username": "fikal",
      "password": "fikal",
      "nomor": "62895630220108"
    },
    {
      "username": "gtw",
      "password": "123",
      "nomor": "6281251162698"
    }
  ]
}
